abnormalities/__init__.py
abnormalities-1.0.2.dist-info/LICENSE
abnormalities-1.0.2.dist-info/METADATA
abnormalities-1.0.2.dist-info/WHEEL
abnormalities-1.0.2.dist-info/top_level.txt
abnormalities-1.0.2.dist-info/RECORD
