Metadata-Version: 2.1
Name: abnormalities
Version: 1.0.2
Summary: patch all exception functions.
Home-page: https://github.com/Kr1s77/abnormalities/
Author: Kris Liang
Author-email: criselyj@163.com
License: UNKNOWN
Platform: UNKNOWN
Classifier: Programming Language :: Python :: 3
Classifier: License :: OSI Approved :: MIT License
License-File: LICENSE
